grndwork_api_client/__init__.py
grndwork_api_client/access_tokens.py
grndwork_api_client/client.py
grndwork_api_client/config.py
grndwork_api_client/content_range.py
grndwork_api_client/interfaces.py
grndwork_api_client/make_paginated_request.py
grndwork_api_client/make_request.py
grndwork_api_client-1.0.0a7.dist-info/LICENSE
grndwork_api_client-1.0.0a7.dist-info/METADATA
grndwork_api_client-1.0.0a7.dist-info/WHEEL
grndwork_api_client-1.0.0a7.dist-info/top_level.txt
grndwork_api_client-1.0.0a7.dist-info/RECORD
