Metadata-Version: 2.1
Name: grndwork-api-client
Version: 1.0.0a7
Summary: Groundwork API Client
Home-page: https://github.com/GroundWorkRenewables/grndwork-api-client
Author: GroundWork Renewables
Author-email: pypi@grndwork.com
Project-URL: Bug Tracker, https://github.com/GroundWorkRenewables/grndwork-api-client/issues
Classifier: Programming Language :: Python :: 3
Classifier: License :: OSI Approved :: MIT License
Classifier: Operating System :: OS Independent
Requires-Python: >=3.9
License-File: LICENSE
Requires-Dist: pyjwt (~=2.4)
Requires-Dist: requests (~=2.27)
